ontocheck/__init__.py
ontocheck/altLabelCheck.py
ontocheck/check_external_data_provider_links_ttl.py
ontocheck/check_for_isolated_elements.py
ontocheck/check_human_readable_license_ttl.py
ontocheck/check_rdf_dump_accessibility_ttl.py
ontocheck/check_sparql_accessibility_ttl.py
ontocheck/cli.py
ontocheck/count_class_connected_components.py
ontocheck/defCheck.py
ontocheck/find_duplicate_labels_from_graph.py
ontocheck/get_properties_missing_domain_and_range.py
ontocheck/leafNodeCheck.py
ontocheck/run_assessment.py
ontocheck/semanticConnection.py
ontocheck/helpers/__init__.py
ontocheck/helpers/helpers.py
ontocheck-0.0.1.4.dist-info/licenses/LICENSE
ontocheck-0.0.1.4.dist-info/METADATA
ontocheck-0.0.1.4.dist-info/WHEEL
ontocheck-0.0.1.4.dist-info/entry_points.txt
ontocheck-0.0.1.4.dist-info/top_level.txt
ontocheck-0.0.1.4.dist-info/RECORD
