Metadata-Version: 2.4
Name: OntoCheck
Version: 0.0.1.4
Summary: A package for assessing the quality and structure of ontologies.
Author-email: "Rishabh Kundu, Van Tran, Redad Mehdi,Erika I. Barcelos, Alp Sehirlioglu, Yinghui Wu, Roger H. French" <mxm1684@case.edu>
Maintainer-email: Redad Mehdi <mxm1684@case.edu>
License: Copyright 2025 SDLE Lab
Project-URL: Homepage, https://github.com/cwru-sdle/OntoCheck
Project-URL: Documentation, https://ontocheck.readthedocs.io/en/latest/index.html
Classifier: Programming Language :: Python :: 3
Classifier: License :: OSI Approved :: MIT License
Classifier: Operating System :: OS Independent
Classifier: Topic :: Scientific/Engineering
Requires-Python: >=3.8
License-File: LICENSE
Requires-Dist: rdflib
Requires-Dist: networkx
Requires-Dist: requests
Dynamic: license-file
